gooddata_metadata_client/__init__.py
gooddata_metadata_client/api_client.py
gooddata_metadata_client/configuration.py
gooddata_metadata_client/exceptions.py
gooddata_metadata_client/model_utils.py
gooddata_metadata_client/rest.py
gooddata_metadata_client/api/__init__.py
gooddata_metadata_client/api/actions_api.py
gooddata_metadata_client/api/analytics_model_api.py
gooddata_metadata_client/api/api_tokens_api.py
gooddata_metadata_client/api/appearance_api.py
gooddata_metadata_client/api/attributes_api.py
gooddata_metadata_client/api/available_drivers_api.py
gooddata_metadata_client/api/context_filters_api.py
gooddata_metadata_client/api/cookie_security_configuration_api.py
gooddata_metadata_client/api/csp_directives_api.py
gooddata_metadata_client/api/dashboards_api.py
gooddata_metadata_client/api/data_filters_api.py
gooddata_metadata_client/api/data_source_declarative_apis_api.py
gooddata_metadata_client/api/data_source_entities_controller_api.py
gooddata_metadata_client/api/data_source_entity_apis_api.py
gooddata_metadata_client/api/datasets_api.py
gooddata_metadata_client/api/dependency_graph_api.py
gooddata_metadata_client/api/entities_api.py
gooddata_metadata_client/api/entitlement_api.py
gooddata_metadata_client/api/facts_api.py
gooddata_metadata_client/api/generate_logical_data_model_api.py
gooddata_metadata_client/api/invalidate_cache_api.py
gooddata_metadata_client/api/labels_api.py
gooddata_metadata_client/api/layout_api.py
gooddata_metadata_client/api/ldm_declarative_apis_api.py
gooddata_metadata_client/api/metrics_api.py
gooddata_metadata_client/api/options_api.py
gooddata_metadata_client/api/organization_controller_api.py
gooddata_metadata_client/api/organization_declarative_apis_api.py
gooddata_metadata_client/api/organization_entity_apis_api.py
gooddata_metadata_client/api/organization_model_controller_api.py
gooddata_metadata_client/api/pdm_declarative_apis_api.py
gooddata_metadata_client/api/permissions_api.py
gooddata_metadata_client-1.3.0.dist-info/LICENSE.txt
gooddata_metadata_client-1.3.0.dist-info/METADATA
gooddata_metadata_client-1.3.0.dist-info/WHEEL
gooddata_metadata_client-1.3.0.dist-info/top_level.txt
gooddata_metadata_client-1.3.0.dist-info/RECORD
